{"chunk_definitions":[{"row":7,"row_count":1,"visible":true,"expansion_state":0,"options":{"engine":"r","label":"setup","include":false},"document_id":"43624145","chunk_id":"csetup_chunk","chunk_label":"setup"},{"row":14,"row_count":1,"visible":true,"expansion_state":0,"options":{"engine":"r","label":"unnamed-chunk-39"},"document_id":"43624145","chunk_id":"ctuj7koetz99h","chunk_label":"unnamed-chunk-1"},{"row":21,"row_count":1,"visible":true,"expansion_state":0,"options":{"engine":"r","label":"unnamed-chunk-40"},"document_id":"43624145","chunk_id":"cztfe12t6lvxz","chunk_label":"unnamed-chunk-2"},{"row":33,"row_count":1,"visible":true,"expansion_state":0,"options":{"engine":"r","label":"unnamed-chunk-41"},"document_id":"43624145","chunk_id":"ce20tf4nov1od","chunk_label":"unnamed-chunk-3"}],"doc_write_time":1627249319,"working_dir":null,"default_chunk_options":{"echo":true}}